AL/__init__.py
AL/omx/__init__.py
AL/omx/_xcommand.py
AL/omx/_xmodifier.py
AL/omx/_xnode.py
AL/omx/_xplug.py
AL/omx/plugin/AL_OMXCommand.py
AL/omx/plugin/__init__.py
AL/omx/tests/__init__.py
AL/omx/tests/runall.py
AL/omx/tests/test_omxundo.py
AL/omx/tests/test_xmodifier.py
AL/omx/tests/test_xnode.py
AL/omx/tests/test_xplug.py
AL/omx/tests/utils/__init__.py
AL/omx/tests/utils/common.py
AL/omx/tests/utils/test_mmodifier.py
AL/omx/tests/utils/test_nodes.py
AL/omx/tests/utils/test_plugs.py
AL/omx/utils/__init__.py
AL/omx/utils/_contexts.py
AL/omx/utils/_exceptions.py
AL/omx/utils/_modifiers.py
AL/omx/utils/_nodes.py
AL/omx/utils/_plugs.py
AL/omx/utils/_stubs.py
AL_omx-1.0.4.dist-info/LICENSE.txt
AL_omx-1.0.4.dist-info/METADATA
AL_omx-1.0.4.dist-info/WHEEL
AL_omx-1.0.4.dist-info/top_level.txt
AL_omx-1.0.4.dist-info/RECORD
