Metadata-Version: 2.1
Name: AL-omx
Version: 1.0.4
Summary: A fast and user-friendly library built on top of Autodesk Maya's OpenMaya library.
Home-page: https://github.com/animallogic/AL_omx
Author: Animal Logic
Author-email: 
License: Apache License, Version 2.0
Classifier: License :: OSI Approved :: Apache Software License
Classifier: Programming Language :: Python :: 3
Classifier: Programming Language :: Python :: 3.7
Classifier: Programming Language :: Python :: 3.9
Classifier: Programming Language :: Python :: 3.10
Classifier: Topic :: Software Development
Classifier: Topic :: Software Development :: Libraries
Classifier: Intended Audience :: Developers
License-File: LICENSE.txt
